hyrule_shield/__init__.py
hyrule_shield/anonymizer.py
hyrule_shield-0.1.2.dist-info/LICENSE
hyrule_shield-0.1.2.dist-info/METADATA
hyrule_shield-0.1.2.dist-info/WHEEL
hyrule_shield-0.1.2.dist-info/entry_points.txt
hyrule_shield-0.1.2.dist-info/top_level.txt
hyrule_shield-0.1.2.dist-info/RECORD
