Metadata-Version: 2.1
Name: hyrule-shield
Version: 0.1.2
Summary: Uma biblioteca para anonimização de informações sensíveis em textos.
Home-page: https://github.com/fynt-io/hyrule-shield
Author: Jader Campos
Author-email: jadercampos@gmail.com
License: MIT
Classifier: Development Status :: 4 - Beta
Classifier: Intended Audience :: Developers
Classifier: License :: OSI Approved :: MIT License
Classifier: Programming Language :: Python :: 3.7
Classifier: Programming Language :: Python :: 3.8
Classifier: Programming Language :: Python :: 3.9
Classifier: Programming Language :: Python :: 3.10
Classifier: Programming Language :: Python :: 3.11
Requires-Python: <4.0,>=3.7
License-File: LICENSE
Requires-Dist: spacy>=3.0.0
Requires-Dist: transformers>=4.0.0
